Metadata-Version: 2.1
Name: ezpickle
Version: 1.0.0
Summary: Helper functions to simplify pickling and unpickling objects to/from files
Home-page: https://github.com/joshburnett/ezpickle
Author: ezpickle
Author-email: github@burnettsonline.org
License: Public Domain
Keywords: pickle unpickle
Platform: UNKNOWN
Classifier: Development Status :: 5 - Production/Stable
Classifier: License :: OSI Approved :: MIT License
Classifier: Programming Language :: Python
Classifier: Programming Language :: Python :: 3
Classifier: Programming Language :: Python :: 3.6
Classifier: Programming Language :: Python :: 3.7
Classifier: Programming Language :: Python :: 3.8
Classifier: Programming Language :: Python :: 3.9
Classifier: Programming Language :: Python :: 3.10
Classifier: Topic :: Utilities
License-File: LICENSE
